Php5MianxiangduixiangChubuDaokeYupeng/README.md
Php5MianxiangduixiangChubuDaokeYupeng/__init__.py
Php5MianxiangduixiangChubuDaokeYupeng/__main__.py
Php5MianxiangduixiangChubuDaokeYupeng/file.pdf
Php5MianxiangduixiangChubuDaokeYupeng/index.html
php5_mianxiangduixiang_chubu_daoke_yupeng-2024.3.2.0.dist-info/METADATA
php5_mianxiangduixiang_chubu_daoke_yupeng-2024.3.2.0.dist-info/WHEEL
php5_mianxiangduixiang_chubu_daoke_yupeng-2024.3.2.0.dist-info/entry_points.txt
php5_mianxiangduixiang_chubu_daoke_yupeng-2024.3.2.0.dist-info/top_level.txt
php5_mianxiangduixiang_chubu_daoke_yupeng-2024.3.2.0.dist-info/RECORD
